{"is_source_file": false, "format": "", "description": "", "external_files": [], "external_methods": [], "published": [], "classes": [], "methods": [], "calls": [], "search-terms": [], "state": 2, "file_id": 12, "knowledge_revision": 49, "git_revision": "5f9c84c65c4a818a9c6483f62b867d2ffa3b5d7c", "hash": "50bda109b20e0da7391a52afb55a7fb2", "format-version": 4, "code-base-name": "frontend_notes_app", "filename": "frontend_notes_app/README.md", "revision_history": [{"49": "5f9c84c65c4a818a9c6483f62b867d2ffa3b5d7c"}]}